{
  "main": {
    "id": "b37ec1457a4d731b",
    "type": "split",
    "children": [
      {
        "id": "0120801da06e1457",
        "type": "tabs",
        "children": [
          {
            "id": "076cdff92be1263f",
            "type": "leaf",
            "state": {
              "type": "markdown",
              "state": {
                "file": "Ditto - getNonce testing.md",
                "mode": "source",
                "source": false
              }
            }
          }
        ]
      }
    ],
    "direction": "vertical"
  },
  "left": {
    "id": "20ff10c1c5df8f8c",
    "type": "split",
    "children": [
      {
        "id": "51f2f18d44e18db6",
        "type": "tabs",
        "children": [
          {
            "id": "f1c1f3dfe30fedbe",
            "type": "leaf",
            "state": {
              "type": "file-explorer",
              "state": {
                "sortOrder": "alphabetical"
              }
            }
          },
          {
            "id": "a25c3c065277647a",
            "type": "leaf",
            "state": {
              "type": "search",
              "state": {
                "query": "",
                "matchingCase": false,
                "explainSearch": false,
                "collapseAll": false,
                "extraContext": false,
                "sortOrder": "alphabetical"
              }
            }
          },
          {
            "id": "14ef7319625d0c87",
            "type": "leaf",
            "state": {
              "type": "bookmarks",
              "state": {}
            }
          }
        ]
      }
    ],
    "direction": "horizontal",
    "width": 300
  },
  "right": {
    "id": "52d18c032714f82a",
    "type": "split",
    "children": [
      {
        "id": "645b32613ca30324",
        "type": "tabs",
        "children": [
          {
            "id": "dbd621440b983880",
            "type": "leaf",
            "state": {
              "type": "backlink",
              "state": {
                "file": "Ditto - getNonce testing.md",
                "collapseAll": false,
                "extraContext": false,
                "sortOrder": "alphabetical",
                "showSearch": false,
                "searchQuery": "",
                "backlinkCollapsed": false,
                "unlinkedCollapsed": true
              }
            }
          },
          {
            "id": "b694ad48390f364c",
            "type": "leaf",
            "state": {
              "type": "outgoing-link",
              "state": {
                "file": "Ditto - getNonce testing.md",
                "linksCollapsed": false,
                "unlinkedCollapsed": true
              }
            }
          },
          {
            "id": "d92496445def70bc",
            "type": "leaf",
            "state": {
              "type": "tag",
              "state": {
                "sortOrder": "frequency",
                "useHierarchy": true
              }
            }
          },
          {
            "id": "d87e8f463316b669",
            "type": "leaf",
            "state": {
              "type": "outline",
              "state": {
                "file": "Ditto - getNonce testing.md"
              }
            }
          }
        ]
      }
    ],
    "direction": "horizontal",
    "width": 300,
    "collapsed": true
  },
  "left-ribbon": {
    "hiddenItems": {
      "obsidian-excalidraw-plugin:Create new drawing": false,
      "switcher:Open quick switcher": false,
      "graph:Open graph view": false,
      "canvas:Create new canvas": false,
      "daily-notes:Open today's daily note": false,
      "templates:Insert template": false,
      "command-palette:Open command palette": false
    }
  },
  "active": "076cdff92be1263f",
  "lastOpenFiles": [
    "Excalidraw/Drawing 2024-01-18 13.52.40.excalidraw.md",
    "Ditto - getNonce testing.md",
    "Excalidraw",
    "💠 Ditto errors handling.md",
    "Deoxys.md",
    "Deoxys-reminder",
    "Welcome.md",
    "Untitled.canvas",
    "create a link.md"
  ]
}